phenum/HNFs.py
phenum/__init__.py
phenum/base.py
phenum/element_data.py
phenum/enumeration.py
phenum/grouptheory.py
phenum/io_utils.py
phenum/makeStr.py
phenum/msg.py
phenum/numerics.py
phenum/phenumStr.py
phenum/phonons.py
phenum/polyaburnside.py
phenum/structures.py
phenum/symmetry.py
phenum/tree.py
phenum/vector_utils.py
phenum/visualize.py
phenum-2.2.0.data/scripts/enumeration.py
phenum-2.2.0.data/scripts/makeStr.py
phenum-2.2.0.data/scripts/phenumStr.py
phenum-2.2.0.dist-info/DESCRIPTION.rst
phenum-2.2.0.dist-info/METADATA
phenum-2.2.0.dist-info/RECORD
phenum-2.2.0.dist-info/WHEEL
phenum-2.2.0.dist-info/metadata.json
phenum-2.2.0.dist-info/top_level.txt
