Metadata-Version: 2.0
Name: phenum
Version: 2.2.0
Summary: Enumeration of symmetrically unique derivative superstructures of crystals.
Home-page: https://github.com/wsmorgan/phonon-enumeration
Author: Wiley S Morgan
Author-email: wiley.s.morgan@gmail.com
License: MIT
Platform: UNKNOWN
Classifier: Development Status :: 5 - Production/Stable
Classifier: Intended Audience :: Science/Research
Classifier: Natural Language :: English
Classifier: License :: OSI Approved :: MIT License
Classifier: Operating System :: MacOS
Classifier: Programming Language :: Python
Classifier: Programming Language :: Python :: 2
Classifier: Programming Language :: Python :: 2.7
Classifier: Programming Language :: Python :: 3
Classifier: Programming Language :: Python :: 3.4
Classifier: Topic :: Scientific/Engineering :: Physics
Requires-Dist: matplotlib
Requires-Dist: numpy
Requires-Dist: pyparsing
Requires-Dist: termcolor
